{"code":"07259","nom":"Saint-Just-d'Ardèche","dept":"07","region":"84","pop":1577,"score":5.2,"classe":"D","data_quality":"complete","score_detail":{"apl":2.455,"apl_national":2.9,"pauvrete":null,"pauvrete_national":0.12,"pct_75_seuls":0.08597293525282707,"pct_75_seuls_national":0.0922,"temps_urgences_min":26.0,"temps_urgences_national":22.0},"medecins":{"generalistes":2,"specialistes":{},"total":2},"manques":null,"domino":null,"jumelles":[{"actions":["MSP installee (1 MSP)"],"apl_apres":2.1,"apl_avant":2.2,"code":"59289","has_msp":true,"nom":"Haussy","similarite":0.99},{"actions":[],"apl_apres":2.6,"apl_avant":2.8,"code":"85268","has_msp":false,"nom":"Saint-Révérend","similarite":1.0},{"actions":[],"apl_apres":2.4,"apl_avant":2.6,"code":"71502","has_msp":false,"nom":"Sassenay","similarite":1.0}],"msp_presente":false,"apl_evolution":{"2015":3.53,"2016":3.27,"2017":3.38,"2018":3.21,"2019":3.4,"2021":2.79,"2022":2.16,"2023":2.46},"pathologies_dept":{"diabete":6.587,"cardiovasculaire":1.9847333333333335,"psychiatrique":1.6715714285714285,"cancers":1.4478125,"respiratoire":5.439},"coords":[44.2904,4.625]}