{"code":"09071","nom":"Cadarcet","dept":"09","region":"76","pop":211,"score":5.0,"classe":"C","data_quality":"complete","score_detail":{"apl":5.392,"apl_national":2.9,"pauvrete":null,"pauvrete_national":0.12,"pct_75_seuls":0.11896758450497932,"pct_75_seuls_national":0.0922,"temps_urgences_min":16.0,"temps_urgences_national":22.0},"medecins":{"generalistes":0,"specialistes":{},"total":0},"manques":null,"domino":null,"jumelles":[{"actions":["APL: 5.0 -> 5.4"],"apl_apres":5.4,"apl_avant":5.0,"code":"65291","has_msp":false,"nom":"Lugagnan","similarite":0.99},{"actions":["APL: 5.1 -> 5.8"],"apl_apres":5.8,"apl_avant":5.1,"code":"32158","has_msp":false,"nom":"L'Isle-Bouzon","similarite":0.99},{"actions":["APL: 2.6 -> 5.8"],"apl_apres":5.8,"apl_avant":2.6,"code":"48053","has_msp":false,"nom":"Cubières","similarite":0.99},{"actions":["APL: 4.5 -> 5.4"],"apl_apres":5.4,"apl_avant":4.5,"code":"64110","has_msp":false,"nom":"Béost","similarite":1.0},{"actions":["APL: 4.5 -> 5.1"],"apl_apres":5.1,"apl_avant":4.5,"code":"70074","has_msp":false,"nom":"Blondefontaine","similarite":0.99}],"msp_presente":false,"apl_evolution":{"2015":5.24,"2016":5.49,"2017":5.37,"2018":5.34,"2019":5.41,"2021":6.64,"2022":5.16,"2023":5.39},"pathologies_dept":{"diabete":6.835,"cardiovasculaire":2.2210666666666663,"psychiatrique":1.6461428571428574,"cancers":1.4009375,"respiratoire":6.992},"coords":[43.0169,1.5012]}