{"code":"11028","nom":"Belcaire","dept":"11","region":"76","pop":365,"score":5.9,"classe":"E","data_quality":"complete","score_detail":{"apl":3.449,"apl_national":2.9,"pauvrete":null,"pauvrete_national":0.12,"pct_75_seuls":0.21010638297872342,"pct_75_seuls_national":0.0922,"temps_urgences_min":34.5,"temps_urgences_national":22.0},"medecins":{"generalistes":1,"specialistes":{},"total":1},"manques":null,"domino":null,"jumelles":[{"actions":["Soins infirmiers a domicile (aide 75+)","APL: 1.4 -> 3.9"],"apl_apres":3.9,"apl_avant":1.4,"code":"09176","has_msp":false,"nom":"Luzenac","similarite":0.99},{"actions":["APL: 2.6 -> 3.4"],"apl_apres":3.4,"apl_avant":2.6,"code":"34201","has_msp":false,"nom":"Pierrerue","similarite":0.99},{"actions":["APL: 2.7 -> 3.3"],"apl_apres":3.3,"apl_avant":2.7,"code":"82059","has_msp":false,"nom":"Faudoas","similarite":0.99},{"actions":["Soins infirmiers a domicile (aide 75+)"],"apl_apres":3.8,"apl_avant":3.8,"code":"12248","has_msp":false,"nom":"Saint-Sernin-sur-Rance","similarite":0.98},{"actions":["APL: 2.1 -> 2.9"],"apl_apres":2.9,"apl_avant":2.1,"code":"43092","has_msp":false,"nom":"Fay-sur-Lignon","similarite":0.99}],"msp_presente":false,"apl_evolution":{"2015":6.67,"2016":6.91,"2017":7.05,"2018":7.07,"2019":7.01,"2021":4.27,"2022":2.91,"2023":3.45},"pathologies_dept":{"diabete":7.637,"cardiovasculaire":2.2265333333333337,"psychiatrique":1.6504285714285716,"cancers":1.4613125,"respiratoire":6.488},"coords":[42.8332,1.9425]}