{"code":"11181","nom":"Labécède-Lauragais","dept":"11","region":"76","pop":420,"score":5.2,"classe":"D","data_quality":"complete","score_detail":{"apl":1.852,"apl_national":2.9,"pauvrete":null,"pauvrete_national":0.12,"pct_75_seuls":0.12541103763943498,"pct_75_seuls_national":0.0922,"temps_urgences_min":15.0,"temps_urgences_national":22.0},"medecins":{"generalistes":0,"specialistes":{},"total":0},"manques":null,"domino":null,"jumelles":[{"actions":["APL: 1.7 -> 2.1"],"apl_apres":2.1,"apl_avant":1.7,"code":"16096","has_msp":false,"nom":"Cherves-Châtelars","similarite":1.0},{"actions":["APL: 1.7 -> 2.3"],"apl_apres":2.3,"apl_avant":1.7,"code":"63043","has_msp":false,"nom":"Blot-l'Église","similarite":0.99},{"actions":["APL: 1.1 -> 1.6"],"apl_apres":1.6,"apl_avant":1.1,"code":"23048","has_msp":false,"nom":"Champagnat","similarite":0.99}],"msp_presente":false,"apl_evolution":{"2015":2.19,"2016":2.12,"2017":2.12,"2018":2.01,"2019":1.88,"2021":1.86,"2022":1.84,"2023":1.85},"pathologies_dept":{"diabete":7.637,"cardiovasculaire":2.2265333333333337,"psychiatrique":1.6504285714285716,"cancers":1.4613125,"respiratoire":6.488},"coords":[43.3985,2.008]}