{"code":"16190","nom":"Longré","dept":"16","region":"75","pop":193,"score":5.7,"classe":"E","data_quality":"complete","score_detail":{"apl":2.561,"apl_national":2.9,"pauvrete":null,"pauvrete_national":0.12,"pct_75_seuls":0.18181818181818193,"pct_75_seuls_national":0.0922,"temps_urgences_min":22.0,"temps_urgences_national":22.0},"medecins":{"generalistes":0,"specialistes":{},"total":0},"manques":null,"domino":null,"jumelles":[{"actions":["APL: 2.6 -> 2.9"],"apl_apres":2.9,"apl_avant":2.6,"code":"86181","has_msp":false,"nom":"Nueil-sous-Faye","similarite":0.99},{"actions":["APL: 2.1 -> 2.5"],"apl_apres":2.5,"apl_avant":2.1,"code":"39184","has_msp":false,"nom":"Les Crozets","similarite":1.0},{"actions":["APL: 2.4 -> 2.8"],"apl_apres":2.8,"apl_avant":2.4,"code":"12235","has_msp":false,"nom":"Saint-Just-sur-Viaur","similarite":1.0},{"actions":["APL: 2.1 -> 2.6"],"apl_apres":2.6,"apl_avant":2.1,"code":"58120","has_msp":false,"nom":"Gâcogne","similarite":0.99},{"actions":["APL: 2.4 -> 3.1"],"apl_apres":3.1,"apl_avant":2.4,"code":"46279","has_msp":false,"nom":"Saint-Maurice-en-Quercy","similarite":0.99}],"msp_presente":false,"apl_evolution":{"2015":2.87,"2016":3.04,"2017":2.8,"2018":2.67,"2019":2.54,"2021":2.53,"2022":2.57,"2023":2.56},"pathologies_dept":{"diabete":7.074,"cardiovasculaire":2.0475333333333334,"psychiatrique":1.3468571428571432,"cancers":1.427875,"respiratoire":6.334},"coords":[45.9949,-0.021]}