{"code":"16248","nom":"Oradour","dept":"16","region":"75","pop":163,"score":5.9,"classe":"E","data_quality":"complete","score_detail":{"apl":2.991,"apl_national":2.9,"pauvrete":null,"pauvrete_national":0.12,"pct_75_seuls":0.21290322580645166,"pct_75_seuls_national":0.0922,"temps_urgences_min":32.0,"temps_urgences_national":22.0},"medecins":{"generalistes":0,"specialistes":{},"total":0},"manques":null,"domino":null,"jumelles":[{"actions":["APL: 2.7 -> 3.2"],"apl_apres":3.2,"apl_avant":2.7,"code":"24327","has_msp":false,"nom":"Pezuls","similarite":0.99},{"actions":["APL: 2.4 -> 2.8"],"apl_apres":2.8,"apl_avant":2.4,"code":"15076","has_msp":false,"nom":"Glénat","similarite":1.0},{"actions":["APL: 2.1 -> 2.9"],"apl_apres":2.9,"apl_avant":2.1,"code":"04204","has_msp":false,"nom":"Senez","similarite":0.99},{"actions":["APL: 2.8 -> 3.3"],"apl_apres":3.3,"apl_avant":2.8,"code":"32199","has_msp":false,"nom":"Lasserrade","similarite":0.99},{"actions":["APL: 2.0 -> 2.5"],"apl_apres":2.5,"apl_avant":2.0,"code":"43098","has_msp":false,"nom":"Freycenet-la-Tour","similarite":0.99}],"msp_presente":false,"apl_evolution":{"2015":3.56,"2016":3.56,"2017":3.19,"2018":3.14,"2019":3.09,"2021":3.22,"2022":3.19,"2023":2.99},"pathologies_dept":{"diabete":7.074,"cardiovasculaire":2.0475333333333334,"psychiatrique":1.3468571428571432,"cancers":1.427875,"respiratoire":6.334},"coords":[45.9119,-0.0329]}