{"code":"19025","nom":"Beyssenac","dept":"19","region":"75","pop":370,"score":5.4,"classe":"D","data_quality":"complete","score_detail":{"apl":2.495,"apl_national":2.9,"pauvrete":null,"pauvrete_national":0.12,"pct_75_seuls":0.13495370880032997,"pct_75_seuls_national":0.0922,"temps_urgences_min":26.0,"temps_urgences_national":22.0},"medecins":{"generalistes":0,"specialistes":{},"total":0},"manques":null,"domino":null,"jumelles":[{"actions":["APL: 2.3 -> 2.6"],"apl_apres":2.6,"apl_avant":2.3,"code":"46154","has_msp":false,"nom":"Laramière","similarite":1.0},{"actions":["APL: 2.0 -> 2.6"],"apl_apres":2.6,"apl_avant":2.0,"code":"46082","has_msp":false,"nom":"Cremps","similarite":1.0},{"actions":["APL: 2.2 -> 2.5"],"apl_apres":2.5,"apl_avant":2.2,"code":"65240","has_msp":false,"nom":"Labatut-Rivière","similarite":0.99},{"actions":["APL: 1.8 -> 2.2"],"apl_apres":2.2,"apl_avant":1.8,"code":"38252","has_msp":false,"nom":"Montchaboud","similarite":0.99},{"actions":["APL: 2.0 -> 2.5"],"apl_apres":2.5,"apl_avant":2.0,"code":"32382","has_msp":false,"nom":"Saint-Jean-Poutge","similarite":0.99}],"msp_presente":false,"apl_evolution":{"2015":3.45,"2016":3.14,"2017":2.91,"2018":2.86,"2019":2.65,"2021":2.52,"2022":2.56,"2023":2.5},"pathologies_dept":{"diabete":7.426,"cardiovasculaire":2.2302666666666666,"psychiatrique":1.7452857142857143,"cancers":1.3951875,"respiratoire":6.681},"coords":[45.4035,1.2954]}