{"code":"19134","nom":"Merlines","dept":"19","region":"75","pop":741,"score":5.7,"classe":"E","data_quality":"complete","score_detail":{"apl":3.614,"apl_national":2.9,"pauvrete":null,"pauvrete_national":0.12,"pct_75_seuls":0.21738671033389154,"pct_75_seuls_national":0.0922,"temps_urgences_min":23.0,"temps_urgences_national":22.0},"medecins":{"generalistes":2,"specialistes":{},"total":2},"manques":null,"domino":null,"jumelles":[{"actions":["MSP installee (1 MSP)","APL: 3.5 -> 3.8"],"apl_apres":3.8,"apl_avant":3.5,"code":"86236","has_msp":true,"nom":"Saint-Pierre-de-Maillé","similarite":1.0},{"actions":["Soins infirmiers a domicile (aide 75+)"],"apl_apres":3.3,"apl_avant":3.4,"code":"23045","has_msp":false,"nom":"Chambon-sur-Voueize","similarite":0.99},{"actions":["MSP installee (1 MSP)"],"apl_apres":3.3,"apl_avant":3.8,"code":"47213","has_msp":true,"nom":"Prayssas","similarite":0.99},{"actions":["APL: 2.3 -> 2.8"],"apl_apres":2.8,"apl_avant":2.3,"code":"86152","has_msp":false,"nom":"Mauprévoir","similarite":0.99},{"actions":["APL: 3.5 -> 3.9"],"apl_apres":3.9,"apl_avant":3.5,"code":"87083","has_msp":false,"nom":"Laurière","similarite":0.99}],"msp_presente":false,"apl_evolution":{"2015":3.63,"2016":3.94,"2017":3.92,"2018":3.79,"2019":4.1,"2021":4.0,"2022":3.63,"2023":3.61},"pathologies_dept":{"diabete":7.426,"cardiovasculaire":2.2302666666666666,"psychiatrique":1.7452857142857143,"cancers":1.3951875,"respiratoire":6.681},"coords":[45.6258,2.4583]}