{"code":"23151","nom":"Peyrat-la-Nonière","dept":"23","region":"75","pop":420,"score":5.8,"classe":"E","data_quality":"complete","score_detail":{"apl":2.059,"apl_national":2.9,"pauvrete":null,"pauvrete_national":0.12,"pct_75_seuls":0.17843066406324667,"pct_75_seuls_national":0.0922,"temps_urgences_min":28.0,"temps_urgences_national":22.0},"medecins":{"generalistes":1,"specialistes":{},"total":1},"manques":null,"domino":null,"jumelles":[{"actions":["APL: 1.7 -> 2.0"],"apl_apres":2.0,"apl_avant":1.7,"code":"64277","has_msp":false,"nom":"Isturits","similarite":0.99},{"actions":["APL: 1.5 -> 2.2"],"apl_apres":2.2,"apl_avant":1.5,"code":"17410","has_msp":false,"nom":"Saint-Thomas-de-Conac","similarite":0.99},{"actions":["APL: 2.0 -> 2.5"],"apl_apres":2.5,"apl_avant":2.0,"code":"43164","has_msp":false,"nom":"Roche-en-Régnier","similarite":0.99},{"actions":["MSP installee (1 MSP)"],"apl_apres":1.6,"apl_avant":1.6,"code":"55517","has_msp":true,"nom":"Seuil-d'Argonne","similarite":0.99},{"actions":["APL: 1.1 -> 1.5"],"apl_apres":1.5,"apl_avant":1.1,"code":"2A163","has_msp":false,"nom":"Monacia-d'Aullène","similarite":0.99}],"msp_presente":false,"apl_evolution":{"2015":3.21,"2016":3.1,"2017":2.7,"2018":2.44,"2019":2.41,"2021":2.02,"2022":2.11,"2023":2.06},"pathologies_dept":{"diabete":9.125,"cardiovasculaire":2.624133333333333,"psychiatrique":2.2544285714285714,"cancers":1.8080624999999997,"respiratoire":7.397},"coords":[46.078,2.2602]}