{"code":"24113","nom":"La Chapelle-Saint-Jean","dept":"24","region":"75","pop":82,"score":5.6,"classe":"E","data_quality":"partial","score_detail":{"apl":2.383,"apl_national":2.9,"pauvrete":null,"pauvrete_national":0.12,"pct_75_seuls":0.14285714285714268,"pct_75_seuls_national":0.0922,"temps_urgences_min":40.0,"temps_urgences_national":22.0},"medecins":{"generalistes":0,"specialistes":{},"total":0},"manques":null,"domino":null,"jumelles":[{"actions":["APL: 2.3 -> 2.6"],"apl_apres":2.6,"apl_avant":2.3,"code":"60271","has_msp":false,"nom":"Gerberoy","similarite":1.0},{"actions":["APL: 2.0 -> 2.7"],"apl_apres":2.7,"apl_avant":2.0,"code":"21430","has_msp":false,"nom":"Montigny-Saint-Barthélemy","similarite":1.0},{"actions":["APL: 1.5 -> 2.5"],"apl_apres":2.5,"apl_avant":1.5,"code":"32023","has_msp":false,"nom":"Avezan","similarite":1.0},{"actions":["APL: 1.6 -> 2.2"],"apl_apres":2.2,"apl_avant":1.6,"code":"70360","has_msp":false,"nom":"Montdoré","similarite":0.99},{"actions":["APL: 1.6 -> 1.9"],"apl_apres":1.9,"apl_avant":1.6,"code":"10134","has_msp":false,"nom":"Échemines","similarite":0.99}],"msp_presente":false,"apl_evolution":{"2015":2.06,"2016":1.48,"2017":1.27,"2018":1.13,"2019":1.13,"2021":2.25,"2022":2.33,"2023":2.38},"pathologies_dept":{"diabete":7.587,"cardiovasculaire":2.2713999999999994,"psychiatrique":1.6967142857142856,"cancers":1.6255625,"respiratoire":6.38},"coords":[45.1957,1.1672]}