{"code":"24199","nom":"Gout-Rossignol","dept":"24","region":"75","pop":360,"score":6.5,"classe":"E","data_quality":"complete","score_detail":{"apl":2.964,"apl_national":2.9,"pauvrete":null,"pauvrete_national":0.12,"pct_75_seuls":0.31755217843755507,"pct_75_seuls_national":0.0922,"temps_urgences_min":46.0,"temps_urgences_national":22.0},"medecins":{"generalistes":1,"specialistes":{},"total":1},"manques":null,"domino":null,"jumelles":[{"actions":["APL: 1.7 -> 2.3"],"apl_apres":2.3,"apl_avant":1.7,"code":"17160","has_msp":false,"nom":"Floirac","similarite":0.99},{"actions":["APL: 2.4 -> 2.9"],"apl_apres":2.9,"apl_avant":2.4,"code":"86172","has_msp":false,"nom":"Mouterre-sur-Blourde","similarite":0.98},{"actions":["MSP installee (1 MSP)"],"apl_apres":4.0,"apl_avant":5.1,"code":"19033","has_msp":true,"nom":"Bugeat","similarite":0.97},{"actions":["APL: 1.1 -> 1.4"],"apl_apres":1.4,"apl_avant":1.1,"code":"79271","has_msp":false,"nom":"Saint-Marc-la-Lande","similarite":0.97},{"actions":["MSP installee (1 MSP)"],"apl_apres":4.7,"apl_avant":4.8,"code":"64533","has_msp":true,"nom":"Tardets-Sorholus","similarite":0.97}],"msp_presente":false,"apl_evolution":{"2015":3.59,"2016":3.54,"2017":3.18,"2018":3.12,"2019":3.05,"2021":2.94,"2022":3.79,"2023":2.96},"pathologies_dept":{"diabete":7.587,"cardiovasculaire":2.2713999999999994,"psychiatrique":1.6967142857142856,"cancers":1.6255625,"respiratoire":6.38},"coords":[45.4129,0.4086]}