{"code":"25307","nom":"Les Hôpitaux-Neufs","dept":"25","region":"27","pop":967,"score":4.0,"classe":"A","data_quality":"complete","score_detail":{"apl":1.959,"apl_national":2.9,"pauvrete":null,"pauvrete_national":0.12,"pct_75_seuls":0.054710994253960615,"pct_75_seuls_national":0.0922,"temps_urgences_min":22.0,"temps_urgences_national":22.0},"medecins":{"generalistes":1,"specialistes":{},"total":1},"manques":null,"domino":null,"jumelles":[{"actions":["Soins infirmiers a domicile (aide 75+)","Bon maillage pharmacies"],"apl_apres":1.8,"apl_avant":1.9,"code":"27089","has_msp":false,"nom":"Thénouville","similarite":1.0},{"actions":[],"apl_apres":2.0,"apl_avant":2.0,"code":"44208","has_msp":false,"nom":"Treffieux","similarite":1.0},{"actions":[],"apl_apres":2.1,"apl_avant":2.2,"code":"78020","has_msp":false,"nom":"Arnouville-lès-Mantes","similarite":1.0}],"msp_presente":false,"apl_evolution":{"2015":3.65,"2016":2.57,"2017":2.5,"2018":1.99,"2019":1.75,"2021":1.99,"2022":1.85,"2023":1.96},"pathologies_dept":{"diabete":6.313,"cardiovasculaire":1.7723333333333329,"psychiatrique":1.139142857142857,"cancers":1.2085000000000001,"respiratoire":5.261},"coords":[46.7853,6.3939]}