{"code":"25449","nom":"Péseux","dept":"25","region":"27","pop":133,"score":5.4,"classe":"D","data_quality":"complete","score_detail":{"apl":1.049,"apl_national":2.9,"pauvrete":null,"pauvrete_national":0.12,"pct_75_seuls":0.08661417322834646,"pct_75_seuls_national":0.0922,"temps_urgences_min":48.0,"temps_urgences_national":22.0},"medecins":{"generalistes":0,"specialistes":{},"total":0},"manques":null,"domino":null,"jumelles":[{"actions":["APL: 0.7 -> 1.2"],"apl_apres":1.2,"apl_avant":0.7,"code":"63344","has_msp":false,"nom":"Saint-Gal-sur-Sioule","similarite":1.0},{"actions":["APL: 0.7 -> 1.5"],"apl_apres":1.5,"apl_avant":0.7,"code":"09190","has_msp":false,"nom":"Mérigon","similarite":0.99},{"actions":[],"apl_apres":1.1,"apl_avant":0.9,"code":"11159","has_msp":false,"nom":"Gaja-la-Selve","similarite":1.0}],"msp_presente":false,"apl_evolution":{"2015":1.97,"2016":1.83,"2017":1.84,"2018":1.19,"2019":1.15,"2021":1.13,"2022":1.13,"2023":1.05},"pathologies_dept":{"diabete":6.313,"cardiovasculaire":1.7723333333333329,"psychiatrique":1.139142857142857,"cancers":1.2085000000000001,"respiratoire":5.261},"coords":[47.3229,6.6859]}