{"code":"27193","nom":"Croth","dept":"27","region":"28","pop":1416,"score":4.8,"classe":"B","data_quality":"complete","score_detail":{"apl":1.894,"apl_national":2.9,"pauvrete":null,"pauvrete_national":0.12,"pct_75_seuls":0.05726365070475752,"pct_75_seuls_national":0.0922,"temps_urgences_min":19.0,"temps_urgences_national":22.0},"medecins":{"generalistes":2,"specialistes":{},"total":2},"manques":null,"domino":null,"jumelles":[{"actions":["APL: 1.4 -> 1.8"],"apl_apres":1.8,"apl_avant":1.4,"code":"38334","has_msp":false,"nom":"Revel","similarite":1.0},{"actions":["MSP installee (1 MSP)"],"apl_apres":2.3,"apl_avant":2.4,"code":"78616","has_msp":true,"nom":"Thoiry","similarite":0.99},{"actions":["MSP installee (1 MSP)"],"apl_apres":2.3,"apl_avant":2.1,"code":"36101","has_msp":true,"nom":"Luant","similarite":0.99}],"msp_presente":false,"apl_evolution":{"2015":2.61,"2016":2.64,"2017":2.5,"2018":2.55,"2019":2.5,"2021":2.05,"2022":1.98,"2023":1.89},"pathologies_dept":{"diabete":6.787,"cardiovasculaire":1.747866666666667,"psychiatrique":1.4034285714285715,"cancers":1.339,"respiratoire":6.624},"coords":[48.8549,1.3708]}