{"code":"29232","nom":"Quimper","dept":"29","region":"53","pop":64385,"score":4.6,"classe":"A","data_quality":"complete","score_detail":{"apl":4.776,"apl_national":2.9,"pauvrete":0.13,"pauvrete_national":0.12,"pct_75_seuls":0.1045608735881994,"pct_75_seuls_national":0.0922,"temps_urgences_min":0.0,"temps_urgences_national":22.0},"medecins":{"generalistes":219,"specialistes":{"Allergologie":null,"Anatomie et cytologie pathologiques":37.0,"Anesthesie-réanimation":40.0,"Anesthésie-réanimation opt anesthésie-pédiatrique":null,"Biologie médicale":3.0,"Biologie médicale option agents infectieux":null,"Biologie médicale option biologie de la reproduction":null,"Biologie médicale option biologie générale":null,"Biologie médicale option hématologie et immunologie":null,"Biologie médicale option médecine moléculaire, génétique et pharmacologie":null,"CHIRURGIE ORALE":null,"Cardiologie et maladies vasculaires":13.0,"Chirurgie générale":2.0,"Chirurgie infantile":1.0,"Chirurgie maxillo-faciale":null,"Chirurgie maxillo-faciale (réforme 2017)":null,"Chirurgie maxillo-faciale et stomatologie":2.0,"Chirurgie orthopédique et traumatologie":17.0,"Chirurgie plastique reconstructrice et esthétique":5.0,"Chirurgie pédiatrique option chirurgie viscérale pédiatrique":null,"Chirurgie pédiatrique option orthopédie pédiatrique":null,"Chirurgie thoracique et cardio-vasculaire":2.0,"Chirurgie urologique":11.0,"Chirurgie vasculaire":1.0,"Chirurgie viscérale et digestive":8.0,"Chirurgie viscérale et digestive opt endo chir":null,"Dermatologie et vénéréologie":10.0,"Endocrinologie et métabolisme":5.0,"Endocrinologie, diabétologie, nutrition":1.0,"Gastro-entérologie et hépatologie":19.0,"Gynéco-obstétrique et Gynéco médicale option Gynéco-médicale":null,"Gynéco-obstétrique et Gynéco médicale option Gynéco-obst":3.0,"Gynécologie médicale":1.0,"Gynécologie médicale et obstétrique":null,"Gynécologie-obstétrique":19.0,"Génétique médicale":null,"Gériatrie":6.0,"Hématologie":3.0,"Hématologie (option Maladie du sang)":2.0,"Hématologie (option Onco-hématologie)":null,"Hématologie (réforme 2017)":null,"Maladies infectieuses et tropicales":1.0,"Méd cardiovasculaire opt card interventionnelle":1.0,"Méd cardiovasculaire opt imagerie cardio d'expert":null,"Méd cardiovasculaire opt rythmo inter stimu card":null,"Médecine d'urgence":8.0,"Médecine du travail":16.0,"Médecine intensive-réanimation":7.0,"Médecine intensive-réanimation opt réa pédiatrique":null,"Médecine interne":6.0,"Médecine interne et immunologie clinique":1.0,"Médecine légale et expertises médicales":null,"Médecine nucléaire":2.0,"Médecine physique et réadaptation":7.0,"Médecine vasculaire":6.0,"Neuro-chirurgie":3.0,"Neuro-psychiatrie":null,"Neurologie":14.0,"Neurologie opt trait interv ischémie céréb aigüe":null,"Néphrologie":10.0,"Néphrologie option soins intensifs néphrologiques":null,"O.R.L et chirurgie cervico faciale":5.0,"ORL - chir cervico-faciale opt audiophonologie":null,"Obstétrique":null,"Oncologie (option onco-hématologie)":null,"Oncologie option médicale":8.0,"Oncologie option radiothérapie":7.0,"Ophtalmologie":18.0,"Ophtalmologie opt chir ophtalmopéd strabologique":null,"Oto-rhino-laryngologie":2.0,"Pneumologie":17.0,"Pneumologie option soins intensifs respiratoires":null,"Psychiatrie":52.0,"Psychiatrie option enfant & adolescent":null,"Psychiatrie option enfant et adolescent":1.0,"Psychiatrie option psychiatrie de la personne âgée":null,"Pédiatrie":31.0,"Pédiatrie option neuropédiatrie":null,"Pédiatrie option néonatologie":null,"Pédiatrie option pneumopédiatrie":null,"Pédiatrie option réanimation pédiatrique":null,"Qualification PAC":null,"Radio-diagnostic":25.0,"Radio-thérapie ":1.0,"Radiologie et imagerie médicale opt radio inter av":1.0,"Recherche médicale":null,"Rhumatologie":11.0,"Santé publique et médecine sociale":3.0,"Santé publique option administration de la santé":null,"Stomatologie":null,"Urologie":null},"total":694},"manques":["cardiologue","psychiatre","oncologue","pneumologue"],"domino":{"medecins_55_plus":208.0,"pct_55_plus":0.2992434855701877,"pct_55_plus_dept":0.2992434855701877,"projection_2030":"-208 medecins (estimation)","effectif_dept_2025":3569,"trend_cagr":1.47,"trend_delta_annuel":47.3},"jumelles":[{"actions":["Maison medicale de garde (urgences proximite)"],"apl_apres":4.5,"apl_avant":4.6,"code":"22113","has_msp":false,"nom":"Lannion","similarite":0.96},{"actions":["MSP installee (1 MSP)","Maison medicale de garde (urgences proximite)","APL: 5.3 -> 5.7"],"apl_apres":5.7,"apl_avant":5.3,"code":"56260","has_msp":true,"nom":"Vannes","similarite":0.96},{"actions":["MSP installee (1 MSP)","Soins infirmiers a domicile (aide 75+)"],"apl_apres":3.9,"apl_avant":4.1,"code":"49099","has_msp":true,"nom":"Cholet","similarite":0.99},{"actions":["MSP installee (4 MSP)","Soins infirmiers a domicile (aide 75+)"],"apl_apres":3.8,"apl_avant":3.8,"code":"85191","has_msp":true,"nom":"La Roche-sur-Yon","similarite":0.99},{"actions":["MSP installee (1 MSP)","Maison medicale de garde (urgences proximite)","Soins infirmiers a domicile (aide 75+)"],"apl_apres":4.1,"apl_avant":3.9,"code":"97101","has_msp":true,"nom":"Les Abymes","similarite":0.98}],"msp_presente":true,"apl_evolution":{"2015":4.75,"2016":4.88,"2017":4.74,"2018":4.58,"2019":4.68,"2021":4.88,"2022":4.47,"2023":4.78},"pathologies_dept":{"diabete":4.976,"cardiovasculaire":1.9369333333333334,"psychiatrique":1.8351428571428572,"cancers":1.546125,"respiratoire":6.489},"coords":[47.9913,-4.098]}