{"code":"30223","nom":"Rousson","dept":"30","region":"76","pop":4456,"score":4.9,"classe":"B","data_quality":"complete","score_detail":{"apl":2.906,"apl_national":2.9,"pauvrete":0.13,"pauvrete_national":0.12,"pct_75_seuls":0.08647398843930636,"pct_75_seuls_national":0.0922,"temps_urgences_min":14.0,"temps_urgences_national":22.0},"medecins":{"generalistes":2,"specialistes":{},"total":2},"manques":null,"domino":null,"jumelles":[{"actions":["MSP installee (1 MSP)"],"apl_apres":2.7,"apl_avant":2.9,"code":"54270","has_msp":true,"nom":"Hussigny-Godbrange","similarite":1.0},{"actions":["APL: 2.3 -> 2.8"],"apl_apres":2.8,"apl_avant":2.3,"code":"38529","has_msp":false,"nom":"Vaulnaveys-le-Haut","similarite":0.99},{"actions":["MSP installee (1 MSP)","Bon maillage pharmacies"],"apl_apres":2.7,"apl_avant":2.8,"code":"27090","has_msp":true,"nom":"Bosroumois","similarite":0.99},{"actions":["MSP installee (2 MSP)"],"apl_apres":3.3,"apl_avant":3.5,"code":"69270","has_msp":true,"nom":"Chaponnay","similarite":0.99},{"actions":["MSP installee (1 MSP)","Soins infirmiers a domicile (aide 75+)","Bon maillage pharmacies"],"apl_apres":3.3,"apl_avant":3.6,"code":"33473","has_msp":true,"nom":"Saint-Savin","similarite":0.99}],"msp_presente":false,"apl_evolution":{"2015":3.58,"2016":3.69,"2017":3.66,"2018":3.64,"2019":3.53,"2021":3.11,"2022":2.93,"2023":2.91},"pathologies_dept":{"diabete":6.765,"cardiovasculaire":1.8810666666666667,"psychiatrique":1.4188571428571428,"cancers":1.32575,"respiratoire":5.934},"coords":[44.2028,4.1449]}