{"code":"31082","nom":"Bourg-Saint-Bernard","dept":"31","region":"76","pop":1125,"score":4.7,"classe":"A","data_quality":"complete","score_detail":{"apl":2.983,"apl_national":2.9,"pauvrete":null,"pauvrete_national":0.12,"pct_75_seuls":0.0636039532215457,"pct_75_seuls_national":0.0922,"temps_urgences_min":22.0,"temps_urgences_national":22.0},"medecins":{"generalistes":2,"specialistes":{},"total":2},"manques":null,"domino":null,"jumelles":[{"actions":["APL: 2.2 -> 2.8"],"apl_apres":2.8,"apl_avant":2.2,"code":"64086","has_msp":false,"nom":"Ayherre","similarite":1.0},{"actions":[],"apl_apres":3.0,"apl_avant":3.2,"code":"72151","has_msp":false,"nom":"Juigné-sur-Sarthe","similarite":1.0},{"actions":["Bon maillage pharmacies"],"apl_apres":3.0,"apl_avant":3.0,"code":"61375","has_msp":false,"nom":"Boischampré","similarite":1.0}],"msp_presente":false,"apl_evolution":{"2015":2.39,"2016":2.58,"2017":3.03,"2018":2.5,"2019":2.69,"2021":2.26,"2022":2.25,"2023":2.98},"pathologies_dept":{"diabete":4.947,"cardiovasculaire":1.4571333333333334,"psychiatrique":1.3861428571428573,"cancers":1.0545,"respiratoire":6.038},"coords":[43.6076,1.6993]}