{"code":"32188","nom":"Lamothe-Goas","dept":"32","region":"76","pop":82,"score":5.1,"classe":"C","data_quality":"partial","score_detail":{"apl":3.277,"apl_national":2.9,"pauvrete":null,"pauvrete_national":0.12,"pct_75_seuls":0.08974358974358976,"pct_75_seuls_national":0.0922,"temps_urgences_min":26.0,"temps_urgences_national":22.0},"medecins":{"generalistes":0,"specialistes":{},"total":0},"manques":null,"domino":null,"jumelles":[{"actions":["APL: 3.1 -> 3.4"],"apl_apres":3.4,"apl_avant":3.1,"code":"82133","has_msp":false,"nom":"Mouillac","similarite":1.0},{"actions":["APL: 2.5 -> 2.9"],"apl_apres":2.9,"apl_avant":2.5,"code":"09013","has_msp":false,"nom":"Arabaux","similarite":1.0},{"actions":["APL: 3.2 -> 3.8"],"apl_apres":3.8,"apl_avant":3.2,"code":"09186","has_msp":false,"nom":"Méras","similarite":0.99},{"actions":["APL: 2.2 -> 3.5"],"apl_apres":3.5,"apl_avant":2.2,"code":"55535","has_msp":false,"nom":"Vaudoncourt","similarite":1.0},{"actions":["APL: 2.6 -> 3.4"],"apl_apres":3.4,"apl_avant":2.6,"code":"39376","has_msp":false,"nom":"Moutoux","similarite":1.0}],"msp_presente":false,"apl_evolution":{"2015":4.09,"2016":3.93,"2017":3.87,"2018":3.9,"2019":3.21,"2021":2.9,"2022":3.58,"2023":3.28},"pathologies_dept":{"diabete":6.808,"cardiovasculaire":2.3383333333333334,"psychiatrique":1.5775714285714284,"cancers":1.4710625,"respiratoire":7.067},"coords":[43.8678,0.5685]}