{"code":"36022","nom":"Bouesse","dept":"36","region":"24","pop":381,"score":5.3,"classe":"D","data_quality":"complete","score_detail":{"apl":3.736,"apl_national":2.9,"pauvrete":null,"pauvrete_national":0.12,"pct_75_seuls":0.13131313131313133,"pct_75_seuls_national":0.0922,"temps_urgences_min":30.0,"temps_urgences_national":22.0},"medecins":{"generalistes":0,"specialistes":{},"total":0},"manques":null,"domino":null,"jumelles":[{"actions":["APL: 3.2 -> 4.1"],"apl_apres":4.1,"apl_avant":3.2,"code":"46152","has_msp":false,"nom":"Lamothe-Fénelon","similarite":0.99},{"actions":[],"apl_apres":3.7,"apl_avant":3.6,"code":"64556","has_msp":false,"nom":"Vielleségure","similarite":1.0},{"actions":[],"apl_apres":3.6,"apl_avant":3.9,"code":"33102","has_msp":false,"nom":"Casseuil","similarite":1.0}],"msp_presente":false,"apl_evolution":{"2015":3.69,"2016":3.57,"2017":3.72,"2018":3.2,"2019":3.31,"2021":3.55,"2022":3.8,"2023":3.74},"pathologies_dept":{"diabete":8.646,"cardiovasculaire":2.3881333333333337,"psychiatrique":1.4774285714285715,"cancers":1.56725,"respiratoire":6.287},"coords":[46.6252,1.6845]}