{"code":"36119","nom":"Mérigny","dept":"36","region":"24","pop":545,"score":6.0,"classe":"E","data_quality":"complete","score_detail":{"apl":3.438,"apl_national":2.9,"pauvrete":null,"pauvrete_national":0.12,"pct_75_seuls":0.30263918768778075,"pct_75_seuls_national":0.0922,"temps_urgences_min":14.0,"temps_urgences_national":22.0},"medecins":{"generalistes":1,"specialistes":{"Allergologie":null,"Anatomie et cytologie pathologiques":null,"Anesthesie-réanimation":1.0,"Anesthésie-réanimation opt anesthésie-pédiatrique":null,"Biologie médicale":null,"Biologie médicale option agents infectieux":null,"Biologie médicale option biologie de la reproduction":null,"Biologie médicale option biologie générale":null,"Biologie médicale option hématologie et immunologie":null,"Biologie médicale option médecine moléculaire, génétique et pharmacologie":null,"CHIRURGIE ORALE":null,"Cardiologie et maladies vasculaires":null,"Chirurgie générale":null,"Chirurgie infantile":null,"Chirurgie maxillo-faciale":null,"Chirurgie maxillo-faciale (réforme 2017)":null,"Chirurgie maxillo-faciale et stomatologie":null,"Chirurgie orthopédique et traumatologie":null,"Chirurgie plastique reconstructrice et esthétique":null,"Chirurgie pédiatrique option chirurgie viscérale pédiatrique":null,"Chirurgie pédiatrique option orthopédie pédiatrique":null,"Chirurgie thoracique et cardio-vasculaire":null,"Chirurgie urologique":null,"Chirurgie vasculaire":null,"Chirurgie viscérale et digestive":null,"Chirurgie viscérale et digestive opt endo chir":null,"Dermatologie et vénéréologie":null,"Endocrinologie et métabolisme":null,"Endocrinologie, diabétologie, nutrition":null,"Gastro-entérologie et hépatologie":null,"Gynéco-obstétrique et Gynéco médicale option Gynéco-médicale":null,"Gynéco-obstétrique et Gynéco médicale option Gynéco-obst":null,"Gynécologie médicale":null,"Gynécologie médicale et obstétrique":null,"Gynécologie-obstétrique":null,"Génétique médicale":null,"Gériatrie":null,"Hématologie":null,"Hématologie (option Maladie du sang)":null,"Hématologie (option Onco-hématologie)":null,"Hématologie (réforme 2017)":null,"Maladies infectieuses et tropicales":null,"Méd cardiovasculaire opt card interventionnelle":null,"Méd cardiovasculaire opt imagerie cardio d'expert":null,"Méd cardiovasculaire opt rythmo inter stimu card":null,"Médecine d'urgence":null,"Médecine du travail":null,"Médecine intensive-réanimation":null,"Médecine intensive-réanimation opt réa pédiatrique":null,"Médecine interne":null,"Médecine interne et immunologie clinique":null,"Médecine légale et expertises médicales":null,"Médecine nucléaire":null,"Médecine physique et réadaptation":null,"Médecine vasculaire":null,"Neuro-chirurgie":null,"Neuro-psychiatrie":null,"Neurologie":null,"Neurologie opt trait interv ischémie céréb aigüe":null,"Néphrologie":null,"Néphrologie option soins intensifs néphrologiques":null,"O.R.L et chirurgie cervico faciale":null,"ORL - chir cervico-faciale opt audiophonologie":null,"Obstétrique":null,"Oncologie (option onco-hématologie)":null,"Oncologie option médicale":null,"Oncologie option radiothérapie":null,"Ophtalmologie":null,"Ophtalmologie opt chir ophtalmopéd strabologique":null,"Oto-rhino-laryngologie":null,"Pneumologie":null,"Pneumologie option soins intensifs respiratoires":null,"Psychiatrie":null,"Psychiatrie option enfant & adolescent":null,"Psychiatrie option enfant et adolescent":null,"Psychiatrie option psychiatrie de la personne âgée":null,"Pédiatrie":null,"Pédiatrie option neuropédiatrie":null,"Pédiatrie option néonatologie":null,"Pédiatrie option pneumopédiatrie":null,"Pédiatrie option réanimation pédiatrique":null,"Qualification PAC":null,"Radio-diagnostic":null,"Radio-thérapie ":null,"Radiologie et imagerie médicale opt radio inter av":null,"Recherche médicale":null,"Rhumatologie":null,"Santé publique et médecine sociale":null,"Santé publique option administration de la santé":null,"Stomatologie":null,"Urologie":null},"total":2},"manques":["endocrinologue","cardiologue","psychiatre","oncologue"],"domino":null,"jumelles":[{"actions":["MSP installee (1 MSP)"],"apl_apres":4.0,"apl_avant":5.1,"code":"19033","has_msp":true,"nom":"Bugeat","similarite":0.99},{"actions":["MSP installee (1 MSP)"],"apl_apres":4.0,"apl_avant":4.0,"code":"15134","has_msp":true,"nom":"Montsalvy","similarite":0.98},{"actions":["APL: 1.7 -> 2.3"],"apl_apres":2.3,"apl_avant":1.7,"code":"17160","has_msp":false,"nom":"Floirac","similarite":0.98},{"actions":["MSP installee (1 MSP)"],"apl_apres":4.7,"apl_avant":4.8,"code":"64533","has_msp":true,"nom":"Tardets-Sorholus","similarite":0.98},{"actions":["MSP installee (1 MSP)","Soins infirmiers a domicile (aide 75+)","Bon maillage pharmacies"],"apl_apres":4.0,"apl_avant":4.0,"code":"12164","has_msp":true,"nom":"Mur-de-Barrez","similarite":0.98}],"msp_presente":false,"apl_evolution":{"2015":4.47,"2016":4.41,"2017":4.29,"2018":4.28,"2019":3.79,"2021":3.76,"2022":3.51,"2023":3.44},"pathologies_dept":{"diabete":8.646,"cardiovasculaire":2.3881333333333337,"psychiatrique":1.4774285714285715,"cancers":1.56725,"respiratoire":6.287},"coords":[46.6341,0.9327]}