{"code":"39238","nom":"Frasne-les-Meulières","dept":"39","region":"27","pop":110,"score":4.6,"classe":"A","data_quality":"complete","score_detail":{"apl":3.402,"apl_national":2.9,"pauvrete":null,"pauvrete_national":0.12,"pct_75_seuls":0.054545454545454494,"pct_75_seuls_national":0.0922,"temps_urgences_min":19.0,"temps_urgences_national":22.0},"medecins":{"generalistes":0,"specialistes":{},"total":0},"manques":null,"domino":null,"jumelles":[{"actions":["APL: 2.8 -> 3.2"],"apl_apres":3.2,"apl_avant":2.8,"code":"21238","has_msp":false,"nom":"Échannay","similarite":0.99},{"actions":["APL: 2.5 -> 3.4"],"apl_apres":3.4,"apl_avant":2.5,"code":"11156","has_msp":false,"nom":"Fraisse-Cabardès","similarite":1.0},{"actions":["APL: 2.3 -> 3.1"],"apl_apres":3.1,"apl_avant":2.3,"code":"55121","has_msp":false,"nom":"Combres-sous-les-Côtes","similarite":1.0},{"actions":["APL: 3.4 -> 3.7"],"apl_apres":3.7,"apl_avant":3.4,"code":"64151","has_msp":false,"nom":"Burgaronne","similarite":0.99},{"actions":["APL: 3.2 -> 3.5"],"apl_apres":3.5,"apl_avant":3.2,"code":"54294","has_msp":false,"nom":"Landremont","similarite":0.99}],"msp_presente":false,"apl_evolution":{"2015":3.76,"2016":3.79,"2017":3.77,"2018":3.79,"2019":4.06,"2021":3.35,"2022":3.65,"2023":3.4},"pathologies_dept":{"diabete":6.676,"cardiovasculaire":2.032066666666667,"psychiatrique":1.4682857142857144,"cancers":1.4599375,"respiratoire":5.483},"coords":[47.1963,5.5035]}