{"code":"42334","nom":"Violay","dept":"42","region":"84","pop":1218,"score":5.4,"classe":"D","data_quality":"complete","score_detail":{"apl":1.207,"apl_national":2.9,"pauvrete":null,"pauvrete_national":0.12,"pct_75_seuls":0.1598058371689822,"pct_75_seuls_national":0.0922,"temps_urgences_min":15.0,"temps_urgences_national":22.0},"medecins":{"generalistes":3,"specialistes":{},"total":3},"manques":null,"domino":null,"jumelles":[{"actions":["Soins infirmiers a domicile (aide 75+)"],"apl_apres":1.6,"apl_avant":1.6,"code":"42015","has_msp":false,"nom":"Belmont-de-la-Loire","similarite":0.99},{"actions":["MSP installee (1 MSP)","Soins infirmiers a domicile (aide 75+)"],"apl_apres":1.3,"apl_avant":1.6,"code":"89441","has_msp":true,"nom":"Vermenton","similarite":0.99},{"actions":["MSP installee (1 MSP)"],"apl_apres":1.5,"apl_avant":1.6,"code":"86224","has_msp":true,"nom":"Saint-Gervais-les-Trois-Clochers","similarite":0.99},{"actions":["APL: 0.4 -> 1.8"],"apl_apres":1.8,"apl_avant":0.4,"code":"39173","has_msp":false,"nom":"Cousance","similarite":0.99},{"actions":["MSP installee (1 MSP)","Bon maillage pharmacies"],"apl_apres":1.8,"apl_avant":3.5,"code":"28018","has_msp":true,"nom":"Authon-du-Perche","similarite":0.99}],"msp_presente":false,"apl_evolution":{"2015":1.55,"2016":1.75,"2017":1.77,"2018":1.69,"2019":1.66,"2021":1.52,"2022":1.17,"2023":1.21},"pathologies_dept":{"diabete":6.764,"cardiovasculaire":1.862333333333333,"psychiatrique":1.5652857142857144,"cancers":1.3047499999999999,"respiratoire":5.807},"coords":[45.8517,4.3486]}