{"code":"46128","nom":"Gramat","dept":"46","region":"76","pop":3512,"score":5.7,"classe":"E","data_quality":"complete","score_detail":{"apl":2.721,"apl_national":2.9,"pauvrete":0.14,"pauvrete_national":0.12,"pct_75_seuls":0.20304385758358706,"pct_75_seuls_national":0.0922,"temps_urgences_min":25.0,"temps_urgences_national":22.0},"medecins":{"generalistes":5,"specialistes":{},"total":5},"manques":null,"domino":{"medecins_55_plus":3.0,"pct_55_plus":0.584493041749503,"pct_55_plus_dept":0.584493041749503,"projection_2030":"-3 medecins (estimation)","effectif_dept_2025":503,"trend_cagr":0.11,"trend_delta_annuel":0.5},"jumelles":[{"actions":["MSP installee (1 MSP)","Soins infirmiers a domicile (aide 75+)"],"apl_apres":3.2,"apl_avant":3.2,"code":"32249","has_msp":true,"nom":"Mauvezin","similarite":0.98},{"actions":["APL: 3.0 -> 3.3"],"apl_apres":3.3,"apl_avant":3.0,"code":"41151","has_msp":false,"nom":"Montrichard Val de Cher","similarite":0.99},{"actions":["MSP installee (1 MSP)","Soins infirmiers a domicile (aide 75+)"],"apl_apres":2.0,"apl_avant":2.1,"code":"71120","has_msp":true,"nom":"Chauffailles","similarite":0.99},{"actions":["MSP installee (1 MSP)"],"apl_apres":2.8,"apl_avant":3.0,"code":"56057","has_msp":true,"nom":"Le Faouët","similarite":0.99},{"actions":["MSP installee (1 MSP)","Soins infirmiers a domicile (aide 75+)"],"apl_apres":3.7,"apl_avant":4.9,"code":"43112","has_msp":true,"nom":"Langeac","similarite":0.99}],"msp_presente":true,"apl_evolution":{"2015":3.69,"2016":4.0,"2017":3.62,"2018":3.77,"2019":3.52,"2021":3.62,"2022":3.4,"2023":2.72},"pathologies_dept":{"diabete":7.035,"cardiovasculaire":2.3335333333333335,"psychiatrique":1.4851428571428573,"cancers":1.584375,"respiratoire":5.903},"coords":[44.7638,1.7254]}