{"code":"47123","nom":"Lacapelle-Biron","dept":"47","region":"75","pop":391,"score":5.5,"classe":"E","data_quality":"complete","score_detail":{"apl":3.383,"apl_national":2.9,"pauvrete":null,"pauvrete_national":0.12,"pct_75_seuls":0.09035548692463176,"pct_75_seuls_national":0.0922,"temps_urgences_min":43.0,"temps_urgences_national":22.0},"medecins":{"generalistes":2,"specialistes":{},"total":2},"manques":null,"domino":null,"jumelles":[{"actions":["APL: 2.8 -> 3.1"],"apl_apres":3.1,"apl_avant":2.8,"code":"64389","has_msp":false,"nom":"Monassut-Audiracq","similarite":1.0},{"actions":["APL: 3.2 -> 3.6"],"apl_apres":3.6,"apl_avant":3.2,"code":"15252","has_msp":false,"nom":"Velzic","similarite":1.0},{"actions":["APL: 3.1 -> 3.7"],"apl_apres":3.7,"apl_avant":3.1,"code":"14088","has_msp":false,"nom":"Bons-Tassilly","similarite":1.0},{"actions":["APL: 2.7 -> 3.0"],"apl_apres":3.0,"apl_avant":2.7,"code":"02261","has_msp":false,"nom":"Dercy","similarite":1.0}],"msp_presente":false,"apl_evolution":{"2015":4.94,"2016":5.28,"2017":5.33,"2018":5.14,"2019":4.6,"2021":4.81,"2022":4.06,"2023":3.38},"pathologies_dept":{"diabete":6.963,"cardiovasculaire":2.1348666666666665,"psychiatrique":1.443714285714286,"cancers":1.4556875,"respiratoire":7.284},"coords":[44.6008,0.9013]}