{"code":"51081","nom":"Branscourt","dept":"51","region":"44","pop":308,"score":4.3,"classe":"A","data_quality":"complete","score_detail":{"apl":3.544,"apl_national":2.9,"pauvrete":null,"pauvrete_national":0.12,"pct_75_seuls":0.04803466141444954,"pct_75_seuls_national":0.0922,"temps_urgences_min":19.0,"temps_urgences_national":22.0},"medecins":{"generalistes":0,"specialistes":{},"total":0},"manques":null,"domino":null,"jumelles":[{"actions":["APL: 2.8 -> 3.7"],"apl_apres":3.7,"apl_avant":2.8,"code":"55481","has_msp":false,"nom":"Senon","similarite":1.0},{"actions":["APL: 3.0 -> 3.4"],"apl_apres":3.4,"apl_avant":3.0,"code":"51140","has_msp":false,"nom":"Chaumuzy","similarite":1.0},{"actions":["APL: 3.2 -> 3.6"],"apl_apres":3.6,"apl_avant":3.2,"code":"61051","has_msp":false,"nom":"Boitron","similarite":1.0},{"actions":["APL: 3.3 -> 4.0"],"apl_apres":4.0,"apl_avant":3.3,"code":"39406","has_msp":false,"nom":"Le Pasquier","similarite":1.0},{"actions":["APL: 3.0 -> 3.4"],"apl_apres":3.4,"apl_avant":3.0,"code":"70507","has_msp":false,"nom":"Trésilley","similarite":0.99}],"msp_presente":false,"apl_evolution":{"2015":3.01,"2016":3.04,"2017":3.11,"2018":3.26,"2019":3.36,"2021":3.5,"2022":3.7,"2023":3.54},"pathologies_dept":{"diabete":7.419,"cardiovasculaire":1.6770666666666665,"psychiatrique":1.1642857142857141,"cancers":1.3125,"respiratoire":6.333},"coords":[49.2743,3.8213]}