{"code":"51227","nom":"Écury-sur-Coole","dept":"51","region":"44","pop":492,"score":4.7,"classe":"A","data_quality":"complete","score_detail":{"apl":1.8,"apl_national":2.9,"pauvrete":null,"pauvrete_national":0.12,"pct_75_seuls":0.09563409563409564,"pct_75_seuls_national":0.0922,"temps_urgences_min":14.0,"temps_urgences_national":22.0},"medecins":{"generalistes":0,"specialistes":{},"total":0},"manques":null,"domino":null,"jumelles":[{"actions":["APL: 1.6 -> 2.0"],"apl_apres":2.0,"apl_avant":1.6,"code":"28362","has_msp":false,"nom":"Saint-Victor-de-Buthon","similarite":1.0},{"actions":["APL: 1.5 -> 1.8"],"apl_apres":1.8,"apl_avant":1.5,"code":"07300","has_msp":false,"nom":"Saint-Thomé","similarite":1.0},{"actions":["APL: 1.4 -> 1.9"],"apl_apres":1.9,"apl_avant":1.4,"code":"16416","has_msp":false,"nom":"Vitrac-Saint-Vincent","similarite":1.0}],"msp_presente":false,"apl_evolution":{"2015":2.1,"2016":2.08,"2017":2.03,"2018":2.04,"2019":1.92,"2021":1.88,"2022":1.86,"2023":1.8},"pathologies_dept":{"diabete":7.419,"cardiovasculaire":1.6770666666666665,"psychiatrique":1.1642857142857141,"cancers":1.3125,"respiratoire":6.333},"coords":[48.8938,4.3339]}