{"code":"51663","nom":"Magenta","dept":"51","region":"44","pop":1680,"score":4.8,"classe":"B","data_quality":"complete","score_detail":{"apl":4.441,"apl_national":2.9,"pauvrete":null,"pauvrete_national":0.12,"pct_75_seuls":0.09649703842685738,"pct_75_seuls_national":0.0922,"temps_urgences_min":6.0,"temps_urgences_national":22.0},"medecins":{"generalistes":4,"specialistes":{},"total":4},"manques":null,"domino":{"medecins_55_plus":1.0,"pct_55_plus":0.3341232227488152,"pct_55_plus_dept":0.3341232227488152,"projection_2030":"-1 medecins (estimation)","effectif_dept_2025":2110,"trend_cagr":0.77,"trend_delta_annuel":15.4},"jumelles":[{"actions":["APL: 3.7 -> 4.1"],"apl_apres":4.1,"apl_avant":3.7,"code":"02292","has_msp":false,"nom":"Étampes-sur-Marne","similarite":0.98},{"actions":["MSP installee (1 MSP)"],"apl_apres":4.0,"apl_avant":4.2,"code":"64526","has_msp":true,"nom":"Soumoulou","similarite":0.98},{"actions":["APL: 3.4 -> 3.8"],"apl_apres":3.8,"apl_avant":3.4,"code":"14354","has_msp":false,"nom":"Langrune-sur-Mer","similarite":0.98},{"actions":["MSP installee (1 MSP)","Soins infirmiers a domicile (aide 75+)"],"apl_apres":3.6,"apl_avant":3.7,"code":"27246","has_msp":true,"nom":"Fleury-sur-Andelle","similarite":0.98}],"msp_presente":false,"apl_evolution":{"2015":5.42,"2016":5.1,"2017":4.92,"2018":5.15,"2019":4.73,"2021":4.64,"2022":4.53,"2023":4.44},"pathologies_dept":{"diabete":7.419,"cardiovasculaire":1.6770666666666665,"psychiatrique":1.1642857142857141,"cancers":1.3125,"respiratoire":6.333},"coords":[49.0554,3.9656]}