{"code":"55242","nom":"Hennemont","dept":"55","region":"44","pop":111,"score":4.8,"classe":"B","data_quality":"complete","score_detail":{"apl":2.997,"apl_national":2.9,"pauvrete":null,"pauvrete_national":0.12,"pct_75_seuls":0.04504504504504501,"pct_75_seuls_national":0.0922,"temps_urgences_min":24.0,"temps_urgences_national":22.0},"medecins":{"generalistes":0,"specialistes":{},"total":0},"manques":null,"domino":null,"jumelles":[{"actions":["APL: 2.3 -> 3.1"],"apl_apres":3.1,"apl_avant":2.3,"code":"55465","has_msp":false,"nom":"Saint-Remy-la-Calonne","similarite":0.99},{"actions":["APL: 2.3 -> 2.9"],"apl_apres":2.9,"apl_avant":2.3,"code":"89410","has_msp":false,"nom":"Tharot","similarite":1.0},{"actions":["APL: 2.3 -> 3.1"],"apl_apres":3.1,"apl_avant":2.3,"code":"61323","has_msp":false,"nom":"Le Pas-Saint-l'Homer","similarite":1.0},{"actions":["APL: 2.0 -> 2.8"],"apl_apres":2.8,"apl_avant":2.0,"code":"39292","has_msp":false,"nom":"Lent","similarite":1.0},{"actions":["APL: 2.6 -> 2.9"],"apl_apres":2.9,"apl_avant":2.6,"code":"70005","has_msp":false,"nom":"Aillevans","similarite":0.99}],"msp_presente":false,"apl_evolution":{"2015":3.44,"2016":2.97,"2017":2.91,"2018":3.62,"2019":2.63,"2021":3.15,"2022":2.49,"2023":3.0},"pathologies_dept":{"diabete":8.02,"cardiovasculaire":2.469066666666667,"psychiatrique":1.2657142857142856,"cancers":1.4520625,"respiratoire":6.856},"coords":[49.1404,5.671]}