{"code":"58016","nom":"Asnois","dept":"58","region":"27","pop":141,"score":5.1,"classe":"C","data_quality":"complete","score_detail":{"apl":2.837,"apl_national":2.9,"pauvrete":null,"pauvrete_national":0.12,"pct_75_seuls":0.14383561643835646,"pct_75_seuls_national":0.0922,"temps_urgences_min":14.0,"temps_urgences_national":22.0},"medecins":{"generalistes":0,"specialistes":{},"total":0},"manques":null,"domino":null,"jumelles":[{"actions":["APL: 2.2 -> 2.6"],"apl_apres":2.6,"apl_avant":2.2,"code":"71057","has_msp":false,"nom":"Bray","similarite":1.0},{"actions":["APL: 2.3 -> 2.9"],"apl_apres":2.9,"apl_avant":2.3,"code":"89234","has_msp":false,"nom":"Lucy-sur-Yonne","similarite":1.0},{"actions":["APL: 2.3 -> 2.9"],"apl_apres":2.9,"apl_avant":2.3,"code":"71537","has_msp":false,"nom":"Thil-sur-Arroux","similarite":0.99},{"actions":["APL: 1.9 -> 2.4"],"apl_apres":2.4,"apl_avant":1.9,"code":"15151","has_msp":false,"nom":"Peyrusse","similarite":0.99},{"actions":["APL: 2.9 -> 3.3"],"apl_apres":3.3,"apl_avant":2.9,"code":"36167","has_msp":false,"nom":"Preuilly-la-Ville","similarite":0.99}],"msp_presente":false,"apl_evolution":{"2015":3.09,"2016":3.11,"2017":3.13,"2018":3.27,"2019":3.22,"2021":3.03,"2022":2.56,"2023":2.84},"pathologies_dept":{"diabete":9.756,"cardiovasculaire":2.422,"psychiatrique":1.7191428571428573,"cancers":1.7639375,"respiratoire":6.386},"coords":[47.4003,3.5903]}