{"code":"61268","nom":"Ménil-Hubert-en-Exmes","dept":"61","region":"28","pop":126,"score":5.3,"classe":"D","data_quality":"complete","score_detail":{"apl":1.831,"apl_national":2.9,"pauvrete":null,"pauvrete_national":0.12,"pct_75_seuls":0.08108108108108113,"pct_75_seuls_national":0.0922,"temps_urgences_min":28.0,"temps_urgences_national":22.0},"medecins":{"generalistes":0,"specialistes":{},"total":0},"manques":null,"domino":null,"jumelles":[{"actions":[],"apl_apres":1.8,"apl_avant":2.1,"code":"02466","has_msp":false,"nom":"Marizy-Sainte-Geneviève","similarite":1.0},{"actions":[],"apl_apres":1.7,"apl_avant":1.8,"code":"02062","has_msp":false,"nom":"Belleau","similarite":1.0},{"actions":[],"apl_apres":1.8,"apl_avant":1.7,"code":"14590","has_msp":false,"nom":"Sainte-Honorine-de-Ducy","similarite":1.0}],"msp_presente":false,"apl_evolution":{"2015":2.09,"2016":2.15,"2017":2.1,"2018":1.87,"2019":1.87,"2021":1.85,"2022":1.89,"2023":1.83},"pathologies_dept":{"diabete":7.326,"cardiovasculaire":2.382533333333334,"psychiatrique":1.465142857142857,"cancers":1.545,"respiratoire":7.12},"coords":[48.8042,0.2355]}