{"code":"62748","nom":"Saint-Folquin","dept":"62","region":"32","pop":2349,"score":4.5,"classe":"A","data_quality":"complete","score_detail":{"apl":4.76,"apl_national":2.9,"pauvrete":null,"pauvrete_national":0.12,"pct_75_seuls":0.056137964063601505,"pct_75_seuls_national":0.0922,"temps_urgences_min":14.5,"temps_urgences_national":22.0},"medecins":{"generalistes":2,"specialistes":{},"total":2},"manques":null,"domino":null,"jumelles":[{"actions":["MSP installee (1 MSP)","Bon maillage pharmacies"],"apl_apres":4.2,"apl_avant":4.2,"code":"87143","has_msp":true,"nom":"Saint-Gence","similarite":0.99},{"actions":["APL: 4.1 -> 4.5"],"apl_apres":4.5,"apl_avant":4.1,"code":"56120","has_msp":false,"nom":"Locqueltas","similarite":0.99},{"actions":[],"apl_apres":4.6,"apl_avant":4.6,"code":"56096","has_msp":false,"nom":"Landaul","similarite":1.0}],"msp_presente":false,"apl_evolution":{"2015":6.33,"2016":6.07,"2017":5.85,"2018":5.67,"2019":5.6,"2021":4.99,"2022":4.72,"2023":4.76},"pathologies_dept":{"diabete":7.995,"cardiovasculaire":1.8431333333333335,"psychiatrique":1.4322857142857142,"cancers":1.2596875,"respiratoire":7.211},"coords":[50.9413,2.1298]}