{"code":"63246","nom":"Murat-le-Quaire","dept":"63","region":"84","pop":484,"score":5.1,"classe":"C","data_quality":"complete","score_detail":{"apl":6.111,"apl_national":2.9,"pauvrete":null,"pauvrete_national":0.12,"pct_75_seuls":0.07581967213114754,"pct_75_seuls_national":0.0922,"temps_urgences_min":40.0,"temps_urgences_national":22.0},"medecins":{"generalistes":1,"specialistes":{},"total":1},"manques":null,"domino":null,"jumelles":[{"actions":["APL: 4.3 -> 5.4"],"apl_apres":5.4,"apl_avant":4.3,"code":"73259","has_msp":false,"nom":"Saint-Martin-sur-la-Chambre","similarite":0.99},{"actions":["APL: 4.6 -> 5.5"],"apl_apres":5.5,"apl_avant":4.6,"code":"63290","has_msp":false,"nom":"Pulvérières","similarite":0.99},{"actions":["APL: 3.1 -> 5.7"],"apl_apres":5.7,"apl_avant":3.1,"code":"73201","has_msp":false,"nom":"Planay","similarite":0.99},{"actions":["APL: 5.0 -> 5.5"],"apl_apres":5.5,"apl_avant":5.0,"code":"14495","has_msp":false,"nom":"Périers-sur-le-Dan","similarite":0.99},{"actions":["APL: 4.5 -> 7.1"],"apl_apres":7.1,"apl_avant":4.5,"code":"23077","has_msp":false,"nom":"Faux-la-Montagne","similarite":0.99}],"msp_presente":false,"apl_evolution":{"2015":3.5,"2016":3.63,"2017":3.47,"2018":3.38,"2019":3.96,"2021":7.08,"2022":6.66,"2023":6.11},"pathologies_dept":{"diabete":6.415,"cardiovasculaire":1.915,"psychiatrique":1.776,"cancers":1.414,"respiratoire":5.792},"coords":[45.6035,2.7565]}