{"code":"64317","nom":"Larressore","dept":"64","region":"75","pop":2163,"score":4.7,"classe":"A","data_quality":"complete","score_detail":{"apl":4.601,"apl_national":2.9,"pauvrete":null,"pauvrete_national":0.12,"pct_75_seuls":0.06791943129738641,"pct_75_seuls_national":0.0922,"temps_urgences_min":19.0,"temps_urgences_national":22.0},"medecins":{"generalistes":4,"specialistes":{},"total":4},"manques":null,"domino":{"medecins_55_plus":1.0,"pct_55_plus":0.33116883116883117,"pct_55_plus_dept":0.33116883116883117,"projection_2030":"-1 medecins (estimation)","effectif_dept_2025":3080,"trend_cagr":1.85,"trend_delta_annuel":50.1},"jumelles":[{"actions":["APL: 4.2 -> 4.6"],"apl_apres":4.6,"apl_avant":4.2,"code":"40264","has_msp":false,"nom":"Saint-Jean-de-Marsacq","similarite":0.99},{"actions":["APL: 4.4 -> 4.8"],"apl_apres":4.8,"apl_avant":4.4,"code":"2A139","has_msp":false,"nom":"Lecci","similarite":1.0},{"actions":["MSP installee (1 MSP)","Soins infirmiers a domicile (aide 75+)"],"apl_apres":4.3,"apl_avant":4.2,"code":"25432","has_msp":true,"nom":"Orchamps-Vennes","similarite":0.99},{"actions":["APL: 4.9 -> 5.2"],"apl_apres":5.2,"apl_avant":4.9,"code":"14060","has_msp":false,"nom":"Bénouville","similarite":0.99},{"actions":["MSP installee (3 MSP)","Bon maillage pharmacies"],"apl_apres":4.9,"apl_avant":4.9,"code":"80316","has_msp":true,"nom":"Flesselles","similarite":0.99}],"msp_presente":false,"apl_evolution":{"2015":3.92,"2016":3.87,"2017":4.28,"2018":3.99,"2019":3.89,"2021":4.53,"2022":4.68,"2023":4.6},"pathologies_dept":{"diabete":5.725,"cardiovasculaire":2.0219333333333336,"psychiatrique":1.6367142857142858,"cancers":1.392625,"respiratoire":7.392},"coords":[43.3719,-1.4428]}