{"code":"68229","nom":"Murbach","dept":"68","region":"44","pop":164,"score":4.4,"classe":"A","data_quality":"complete","score_detail":{"apl":0.91,"apl_national":2.9,"pauvrete":null,"pauvrete_national":0.12,"pct_75_seuls":0.04242424242424244,"pct_75_seuls_national":0.0922,"temps_urgences_min":10.0,"temps_urgences_national":22.0},"medecins":{"generalistes":0,"specialistes":{},"total":0},"manques":null,"domino":null,"jumelles":[{"actions":["APL: 0.2 -> 1.0"],"apl_apres":1.0,"apl_avant":0.2,"code":"07003","has_msp":false,"nom":"Aizac","similarite":1.0},{"actions":[],"apl_apres":1.0,"apl_avant":1.0,"code":"21665","has_msp":false,"nom":"Vernois-lès-Vesvres","similarite":1.0},{"actions":[],"apl_apres":0.8,"apl_avant":0.6,"code":"22365","has_msp":false,"nom":"Trémargat","similarite":1.0}],"msp_presente":false,"apl_evolution":{"2015":1.18,"2016":1.17,"2017":1.16,"2018":1.1,"2019":1.08,"2021":0.77,"2022":0.91,"2023":0.91},"pathologies_dept":{"diabete":7.516,"cardiovasculaire":2.063066666666667,"psychiatrique":1.3335714285714286,"cancers":1.26275,"respiratoire":5.354},"coords":[47.9156,7.137]}