{"code":"72182","nom":"Mansigné","dept":"72","region":"52","pop":1555,"score":5.7,"classe":"E","data_quality":"complete","score_detail":{"apl":1.799,"apl_national":2.9,"pauvrete":null,"pauvrete_national":0.12,"pct_75_seuls":0.16575030235247623,"pct_75_seuls_national":0.0922,"temps_urgences_min":34.0,"temps_urgences_national":22.0},"medecins":{"generalistes":1,"specialistes":{},"total":1},"manques":null,"domino":null,"jumelles":[{"actions":["Soins infirmiers a domicile (aide 75+)"],"apl_apres":1.6,"apl_avant":1.6,"code":"42015","has_msp":false,"nom":"Belmont-de-la-Loire","similarite":1.0},{"actions":["MSP installee (1 MSP)","Bon maillage pharmacies"],"apl_apres":2.2,"apl_avant":2.1,"code":"39128","has_msp":true,"nom":"Chaussin","similarite":1.0},{"actions":["MSP installee (1 MSP)","Bon maillage pharmacies"],"apl_apres":1.5,"apl_avant":1.7,"code":"24553","has_msp":true,"nom":"Tocane-Saint-Apre","similarite":0.99},{"actions":["Soins infirmiers a domicile (aide 75+)"],"apl_apres":1.8,"apl_avant":2.1,"code":"47054","has_msp":false,"nom":"Castelmoron-sur-Lot","similarite":0.99},{"actions":["MSP installee (1 MSP)","Bon maillage pharmacies"],"apl_apres":2.1,"apl_avant":2.1,"code":"03155","has_msp":true,"nom":"Lurcy-Lévis","similarite":0.99}],"msp_presente":false,"apl_evolution":{"2015":2.47,"2016":2.43,"2017":2.2,"2018":2.27,"2019":2.35,"2021":2.14,"2022":1.92,"2023":1.8},"pathologies_dept":{"diabete":6.634,"cardiovasculaire":1.7533333333333336,"psychiatrique":1.3444285714285715,"cancers":1.4605000000000001,"respiratoire":5.589},"coords":[47.7512,0.1283]}