{"code":"73286","nom":"Serrières-en-Chautagne","dept":"73","region":"84","pop":1156,"score":5.0,"classe":"C","data_quality":"complete","score_detail":{"apl":3.241,"apl_national":2.9,"pauvrete":null,"pauvrete_national":0.12,"pct_75_seuls":0.0770726774476457,"pct_75_seuls_national":0.0922,"temps_urgences_min":27.0,"temps_urgences_national":22.0},"medecins":{"generalistes":1,"specialistes":{},"total":1},"manques":null,"domino":null,"jumelles":[{"actions":["APL: 2.6 -> 3.1"],"apl_apres":3.1,"apl_avant":2.6,"code":"38212","has_msp":false,"nom":"Livet-et-Gavet","similarite":1.0},{"actions":["APL: 2.6 -> 3.5"],"apl_apres":3.5,"apl_avant":2.6,"code":"38407","has_msp":false,"nom":"La Sure en Chartreuse","similarite":1.0},{"actions":["APL: 2.8 -> 3.1"],"apl_apres":3.1,"apl_avant":2.8,"code":"60590","has_msp":false,"nom":"Saint-Omer-en-Chaussée","similarite":1.0}],"msp_presente":false,"apl_evolution":{"2015":2.88,"2016":2.76,"2017":3.05,"2018":3.07,"2019":2.73,"2021":3.25,"2022":2.88,"2023":3.24},"pathologies_dept":{"diabete":5.17,"cardiovasculaire":1.6622666666666668,"psychiatrique":1.3184285714285715,"cancers":1.3054999999999999,"respiratoire":4.497},"coords":[45.8752,5.8452]}