{"code":"76378","nom":"Jumièges","dept":"76","region":"28","pop":1761,"score":5.2,"classe":"D","data_quality":"complete","score_detail":{"apl":2.678,"apl_national":2.9,"pauvrete":null,"pauvrete_national":0.12,"pct_75_seuls":0.10544072181305439,"pct_75_seuls_national":0.0922,"temps_urgences_min":32.5,"temps_urgences_national":22.0},"medecins":{"generalistes":1,"specialistes":{},"total":1},"manques":null,"domino":null,"jumelles":[{"actions":["MSP installee (1 MSP)"],"apl_apres":2.7,"apl_avant":2.6,"code":"76614","has_msp":true,"nom":"Saint-Martin-de-Boscherville","similarite":1.0},{"actions":["MSP installee (1 MSP)"],"apl_apres":2.9,"apl_avant":2.7,"code":"22208","has_msp":true,"nom":"Plouasne","similarite":1.0},{"actions":["MSP installee (1 MSP)"],"apl_apres":2.6,"apl_avant":2.8,"code":"01303","has_msp":true,"nom":"Poncin","similarite":1.0},{"actions":["MSP installee (1 MSP)","Soins infirmiers a domicile (aide 75+)","Bon maillage pharmacies"],"apl_apres":2.7,"apl_avant":2.6,"code":"84025","has_msp":true,"nom":"Cabrières-d'Avignon","similarite":1.0},{"actions":["APL: 2.4 -> 3.0"],"apl_apres":3.0,"apl_avant":2.4,"code":"62204","has_msp":false,"nom":"Campagne-lès-Hesdin","similarite":1.0}],"msp_presente":false,"apl_evolution":{"2015":2.79,"2016":2.74,"2017":2.78,"2018":2.65,"2019":2.69,"2021":2.59,"2022":2.71,"2023":2.68},"pathologies_dept":{"diabete":6.907,"cardiovasculaire":1.7856,"psychiatrique":1.6498571428571431,"cancers":1.315375,"respiratoire":7.422},"coords":[49.4305,0.8313]}