{"code":"77216","nom":"Grez-sur-Loing","dept":"77","region":"11","pop":1432,"score":4.5,"classe":"A","data_quality":"complete","score_detail":{"apl":3.826,"apl_national":2.9,"pauvrete":null,"pauvrete_national":0.12,"pct_75_seuls":0.08567500730338634,"pct_75_seuls_national":0.0922,"temps_urgences_min":9.0,"temps_urgences_national":22.0},"medecins":{"generalistes":0,"specialistes":{},"total":0},"manques":null,"domino":null,"jumelles":[{"actions":["MSP installee (1 MSP)","Soins infirmiers a domicile (aide 75+)"],"apl_apres":3.4,"apl_avant":3.5,"code":"55154","has_msp":true,"nom":"Dieue-sur-Meuse","similarite":1.0},{"actions":["MSP installee (1 MSP)","APL: 3.0 -> 3.6"],"apl_apres":3.6,"apl_avant":3.0,"code":"15196","has_msp":true,"nom":"Saint-Mamet-la-Salvetat","similarite":0.99},{"actions":["MSP installee (1 MSP)","APL: 2.8 -> 3.8"],"apl_apres":3.8,"apl_avant":2.8,"code":"73105","has_msp":true,"nom":"Les Échelles","similarite":0.99}],"msp_presente":false,"apl_evolution":{"2015":3.97,"2016":4.17,"2017":4.06,"2018":3.97,"2019":4.23,"2021":3.99,"2022":3.92,"2023":3.83},"pathologies_dept":{"diabete":6.301,"cardiovasculaire":1.3282,"psychiatrique":1.0728571428571427,"cancers":1.1280625,"respiratoire":5.758},"coords":[48.3075,2.6816]}