{"code":"77357","nom":"Pécy","dept":"77","region":"11","pop":849,"score":4.7,"classe":"A","data_quality":"complete","score_detail":{"apl":1.717,"apl_national":2.9,"pauvrete":null,"pauvrete_national":0.12,"pct_75_seuls":0.06390532544378698,"pct_75_seuls_national":0.0922,"temps_urgences_min":22.0,"temps_urgences_national":22.0},"medecins":{"generalistes":0,"specialistes":{},"total":0},"manques":null,"domino":null,"jumelles":[{"actions":["APL: 1.3 -> 1.8"],"apl_apres":1.8,"apl_avant":1.3,"code":"79284","has_msp":false,"nom":"Sainte-Ouenne","similarite":1.0},{"actions":[],"apl_apres":1.8,"apl_avant":2.3,"code":"53074","has_msp":false,"nom":"Contest","similarite":1.0},{"actions":[],"apl_apres":1.7,"apl_avant":1.7,"code":"14672","has_msp":false,"nom":"Val de Drôme","similarite":1.0}],"msp_presente":false,"apl_evolution":{"2015":2.07,"2016":2.09,"2017":1.95,"2018":1.92,"2019":1.9,"2021":1.91,"2022":1.9,"2023":1.72},"pathologies_dept":{"diabete":6.301,"cardiovasculaire":1.3282,"psychiatrique":1.0728571428571427,"cancers":1.1280625,"respiratoire":5.758},"coords":[48.6443,3.0673]}