{"code":"80470","nom":"Léalvillers","dept":"80","region":"32","pop":156,"score":5.0,"classe":"C","data_quality":"complete","score_detail":{"apl":3.42,"apl_national":2.9,"pauvrete":null,"pauvrete_national":0.12,"pct_75_seuls":0.10843373493975883,"pct_75_seuls_national":0.0922,"temps_urgences_min":22.0,"temps_urgences_national":22.0},"medecins":{"generalistes":0,"specialistes":{},"total":0},"manques":null,"domino":null,"jumelles":[{"actions":["APL: 3.0 -> 3.6"],"apl_apres":3.6,"apl_avant":3.0,"code":"14284","has_msp":false,"nom":"Fourneaux-le-Val","similarite":1.0},{"actions":["APL: 2.6 -> 3.1"],"apl_apres":3.1,"apl_avant":2.6,"code":"70576","has_msp":false,"nom":"Vougécourt","similarite":1.0},{"actions":["APL: 2.5 -> 3.5"],"apl_apres":3.5,"apl_avant":2.5,"code":"15080","has_msp":false,"nom":"Joursac","similarite":0.99},{"actions":["APL: 2.7 -> 3.2"],"apl_apres":3.2,"apl_avant":2.7,"code":"09251","has_msp":false,"nom":"Roumengoux","similarite":0.99},{"actions":["APL: 2.4 -> 3.0"],"apl_apres":3.0,"apl_avant":2.4,"code":"82104","has_msp":false,"nom":"Marsac","similarite":0.99}],"msp_presente":false,"apl_evolution":{"2015":3.07,"2016":2.85,"2017":3.44,"2018":3.19,"2019":3.1,"2021":3.18,"2022":3.36,"2023":3.42},"pathologies_dept":{"diabete":7.881,"cardiovasculaire":1.8126,"psychiatrique":1.458714285714286,"cancers":1.2786875,"respiratoire":6.907},"coords":[50.0684,2.5081]}