{"code":"87146","nom":"Saint-Germain-les-Belles","dept":"87","region":"75","pop":1150,"score":5.7,"classe":"E","data_quality":"complete","score_detail":{"apl":3.674,"apl_national":2.9,"pauvrete":null,"pauvrete_national":0.12,"pct_75_seuls":0.19689361345868653,"pct_75_seuls_national":0.0922,"temps_urgences_min":28.0,"temps_urgences_national":22.0},"medecins":{"generalistes":2,"specialistes":{},"total":2},"manques":null,"domino":null,"jumelles":[{"actions":["MSP installee (1 MSP)"],"apl_apres":3.3,"apl_avant":3.3,"code":"16409","has_msp":true,"nom":"Villefagnan","similarite":0.99},{"actions":["MSP installee (3 MSP)","APL: 4.0 -> 4.3"],"apl_apres":4.3,"apl_avant":4.0,"code":"17243","has_msp":true,"nom":"Montlieu-la-Garde","similarite":0.99},{"actions":["APL: 2.6 -> 3.2"],"apl_apres":3.2,"apl_avant":2.6,"code":"24328","has_msp":false,"nom":"Piégut-Pluviers","similarite":0.99},{"actions":["MSP installee (1 MSP)","Soins infirmiers a domicile (aide 75+)","APL: 3.5 -> 4.0"],"apl_apres":4.0,"apl_avant":3.5,"code":"64513","has_msp":true,"nom":"Sauveterre-de-Béarn","similarite":0.99},{"actions":["APL: 2.6 -> 2.9"],"apl_apres":2.9,"apl_avant":2.6,"code":"86061","has_msp":false,"nom":"Charroux","similarite":0.99}],"msp_presente":false,"apl_evolution":{"2015":4.53,"2016":4.56,"2017":4.03,"2018":4.01,"2019":3.82,"2021":3.56,"2022":3.17,"2023":3.67},"pathologies_dept":{"diabete":7.401,"cardiovasculaire":2.0407333333333333,"psychiatrique":1.8745714285714286,"cancers":1.6474375,"respiratoire":6.354},"coords":[45.6036,1.4858]}