{"code":"88437","nom":"Saint-Vallier","dept":"88","region":"44","pop":100,"score":5.0,"classe":"C","data_quality":"complete","score_detail":{"apl":2.861,"apl_national":2.9,"pauvrete":null,"pauvrete_national":0.12,"pct_75_seuls":0.06,"pct_75_seuls_national":0.0922,"temps_urgences_min":22.0,"temps_urgences_national":22.0},"medecins":{"generalistes":0,"specialistes":{},"total":0},"manques":null,"domino":null,"jumelles":[{"actions":["APL: 2.3 -> 3.1"],"apl_apres":3.1,"apl_avant":2.3,"code":"55121","has_msp":false,"nom":"Combres-sous-les-Côtes","similarite":0.99},{"actions":["APL: 2.2 -> 2.7"],"apl_apres":2.7,"apl_avant":2.2,"code":"51309","has_msp":false,"nom":"Jonquery","similarite":0.99},{"actions":["APL: 1.5 -> 2.4"],"apl_apres":2.4,"apl_avant":1.5,"code":"55299","has_msp":false,"nom":"Loison","similarite":0.99},{"actions":["APL: 2.5 -> 3.0"],"apl_apres":3.0,"apl_avant":2.5,"code":"39281","has_msp":false,"nom":"Le Latet","similarite":1.0},{"actions":["APL: 2.3 -> 2.8"],"apl_apres":2.8,"apl_avant":2.3,"code":"31001","has_msp":false,"nom":"Agassac","similarite":1.0}],"msp_presente":false,"apl_evolution":{"2015":3.07,"2016":3.0,"2017":2.96,"2018":3.02,"2019":2.74,"2021":2.91,"2022":3.05,"2023":2.86},"pathologies_dept":{"diabete":7.582,"cardiovasculaire":2.2492000000000005,"psychiatrique":1.3728571428571428,"cancers":1.4073125,"respiratoire":6.573},"coords":[48.2737,6.3149]}