{"code":"93074","nom":"Vaujours","dept":"93","region":"11","pop":8007,"score":4.7,"classe":"A","data_quality":"complete","score_detail":{"apl":2.407,"apl_national":2.9,"pauvrete":0.14,"pauvrete_national":0.12,"pct_75_seuls":0.05946024194471468,"pct_75_seuls_national":0.0922,"temps_urgences_min":13.0,"temps_urgences_national":22.0},"medecins":{"generalistes":5,"specialistes":{},"total":5},"manques":null,"domino":{"medecins_55_plus":2.0,"pct_55_plus":0.46899801587301587,"pct_55_plus_dept":0.46899801587301587,"projection_2030":"-2 medecins (estimation)","effectif_dept_2025":4032,"trend_cagr":-0.43,"trend_delta_annuel":-17.9},"jumelles":[{"actions":["Maison medicale de garde (urgences proximite)","Soins infirmiers a domicile (aide 75+)"],"apl_apres":2.3,"apl_avant":2.4,"code":"95052","has_msp":false,"nom":"Beaumont-sur-Oise","similarite":0.98},{"actions":["MSP installee (1 MSP)"],"apl_apres":2.3,"apl_avant":2.5,"code":"91552","has_msp":true,"nom":"Saint-Germain-lès-Arpajon","similarite":0.98},{"actions":["MSP installee (1 MSP)","Bon maillage pharmacies"],"apl_apres":2.7,"apl_avant":2.7,"code":"95539","has_msp":true,"nom":"Saint-Brice-sous-Forêt","similarite":0.97},{"actions":["MSP installee (1 MSP)","Bon maillage pharmacies"],"apl_apres":2.0,"apl_avant":2.4,"code":"95351","has_msp":true,"nom":"Louvres","similarite":0.97},{"actions":["MSP installee (1 MSP)"],"apl_apres":2.7,"apl_avant":2.7,"code":"95288","has_msp":true,"nom":"Groslay","similarite":0.97}],"msp_presente":false,"apl_evolution":{"2015":3.1,"2016":3.08,"2017":2.85,"2018":2.87,"2019":2.8,"2021":2.41,"2022":2.38,"2023":2.41},"pathologies_dept":{"diabete":7.64,"cardiovasculaire":1.1545999999999998,"psychiatrique":1.0892857142857142,"cancers":0.8463750000000001,"respiratoire":5.395},"coords":[48.9353,2.5771]}